cdk8s_plus_32/__init__.py
cdk8s_plus_32/py.typed
cdk8s_plus_32/_jsii/__init__.py
cdk8s_plus_32/_jsii/cdk8s-plus-32@2.5.21.jsii.tgz
cdk8s_plus_32/k8s/__init__.py
cdk8s_plus_32-2.5.21.dist-info/LICENSE
cdk8s_plus_32-2.5.21.dist-info/METADATA
cdk8s_plus_32-2.5.21.dist-info/NOTICE
cdk8s_plus_32-2.5.21.dist-info/WHEEL
cdk8s_plus_32-2.5.21.dist-info/top_level.txt
cdk8s_plus_32-2.5.21.dist-info/RECORD
